geoarrow/rust/io/__init__.py
geoarrow/rust/io/_csv.pyi
geoarrow/rust/io/_flatgeobuf.pyi
geoarrow/rust/io/_geojson.pyi
geoarrow/rust/io/_io.cpython-314-i386-linux-gnu.so
geoarrow/rust/io/_io.pyi
geoarrow/rust/io/_parquet.pyi
geoarrow/rust/io/_postgis.pyi
geoarrow/rust/io/_shapefile.pyi
geoarrow/rust/io/enums.py
geoarrow/rust/io/py.typed
geoarrow/rust/io/types.py
geoarrow_rust_io-0.6.1.dist-info/METADATA
geoarrow_rust_io-0.6.1.dist-info/WHEEL
geoarrow_rust_io-0.6.1.dist-info/RECORD
